fliscopt/_Flight.py
fliscopt/__init__.py
fliscopt/_testbase.py
fliscopt/base_algorithm.py
fliscopt/chaining.py
fliscopt/fitness.py
fliscopt/ga.py
fliscopt/hc.py
fliscopt/multiproc.py
fliscopt/rs.py
fliscopt/sa.py
fliscopt/utils/__init__.py
fliscopt/utils/ga_utils.py
fliscopt/utils/util.py
tests/__init__.py
tests/test_algorithms.py
tests/test_chaining.py
tests/test_fitness.py
fliscopt-0.3.0.dist-info/LICENSE
fliscopt-0.3.0.dist-info/METADATA
fliscopt-0.3.0.dist-info/WHEEL
fliscopt-0.3.0.dist-info/top_level.txt
fliscopt-0.3.0.dist-info/RECORD
