Metadata-Version: 2.1
Name: fliscopt
Version: 0.3.0
Summary: Flight scheduling optimization using Genetic Algorithm variants and other algorithms. 
Home-page: UNKNOWN
Author: Ankit Grover, Jones Granatyr
Author-email: agrover112@gmail.com
License: MIT
Platform: linux
Platform: macos
Platform: unix
Requires-Python: >=3.7.10
License-File: LICENSE
Requires-Dist: matplotlib
Requires-Dist: rich
